[
    {
        "id": "ec5b0dad.e19758",
        "type": "tab",
        "label": "Flow 1"
    },
    {
        "id": "b9600f05.ba9e28",
        "type": "http in",
        "z": "ec5b0dad.e19758",
        "name": "",
        "url": "/readings-form",
        "method": "post",
        "swaggerDoc": "",
        "x": 192,
        "y": 214,
        "wires": [
            [
                "eca0cc0b.36b66",
                "2a1265ea.73cde2"
            ]
        ]
    },
    {
        "id": "eca0cc0b.36b66",
        "type": "template",
        "z": "ec5b0dad.e19758",
        "name": "page",
        "field": "payload",
        "fieldType": "msg",
        "format": "json",
        "syntax": "mustache",
        "template": "{\"sensorID\":\"{{req.query.id}}\",\"sensorType\":\"room_temperature\",\"value\":{{req.query.temp}},\"timestamp\":{{req.query.timestamp}},\"daydate\":{{req.query.daydate}}}\n",
        "x": 445,
        "y": 208,
        "wires": [
            [
                "b4b31465.f06c5"
            ]
        ]
    },
    {
        "id": "b4b31465.f06c5",
        "type": "change",
        "z": "ec5b0dad.e19758",
        "name": "Set Headers",
        "rules": [
            {
                "t": "set",
                "p": "headers",
                "pt": "msg",
                "to": "{}",
                "tot": "json"
            },
            {
                "t": "set",
                "p": "headers.content-type",
                "pt": "msg",
                "to": "application/json",
                "tot": "str"
            }
        ],
        "action": "",
        "property": "",
        "from": "",
        "to": "",
        "reg": false,
        "x": 660,
        "y": 212,
        "wires": [
            [
                "cd5f8157.317928",
                "6c36eed0.5017d8",
                "7519a4c3.c03a7c"
            ]
        ]
    },
    {
        "id": "cd5f8157.317928",
        "type": "http response",
        "z": "ec5b0dad.e19758",
        "name": "",
        "x": 857,
        "y": 205,
        "wires": []
    },
    {
        "id": "6c36eed0.5017d8",
        "type": "debug",
        "z": "ec5b0dad.e19758",
        "name": "",
        "active": true,
        "console": "false",
        "complete": "payload",
        "x": 881.5,
        "y": 385,
        "wires": []
    },
    {
        "id": "2a1265ea.73cde2",
        "type": "template",
        "z": "ec5b0dad.e19758",
        "name": "lux page",
        "field": "payload",
        "fieldType": "msg",
        "format": "json",
        "syntax": "mustache",
        "template": "{\"sensorID\":\"{{req.query.id}}\",\"sensorType\":\"luxometer\",\"value\":{{req.query.lux}},\"timestamp\":{{req.query.timestamp}},\"daydate\":{{req.query.daydate}}}\n",
        "x": 466.5,
        "y": 364,
        "wires": [
            [
                "6c36eed0.5017d8",
                "7519a4c3.c03a7c"
            ]
        ]
    },
    {
        "id": "7519a4c3.c03a7c",
        "type": "kafka",
        "z": "ec5b0dad.e19758",
        "zkquorum": "127.0.0.1:9092",
        "topics": "SensorReadings",
        "debug": "",
        "x": 1185,
        "y": 331,
        "wires": []
    }
]
